LICENSE
textual_select/__init__.py
textual_select/_select.py
textual_select-0.3.4.dist-info/LICENSE
textual_select-0.3.4.dist-info/WHEEL
textual_select-0.3.4.dist-info/METADATA
textual_select-0.3.4.dist-info/RECORD
